<?xml version="1.0" encoding="utf-8"?>
<soap:Envelope
  xmlns:soap="http://schemas.xmlsoap.org/soap/envelope/"
  xmlns:xsi="http://www.w3.org/2001/XMLSchema-instance"
  xmlns:xsd="http://www.w3.org/2001/XMLSchema">
  <soap:Body>
    <SaveCompaniesResponse xmlns="http://24sevenOffice.com/webservices">
      <SaveCompaniesResult>
        <Company>
          <Id>5678</Id>
          <Name>Test Company</Name>
        </Company>
      </SaveCompaniesResult>
    </SaveCompaniesResponse>
  </soap:Body>
</soap:Envelope>
